<?xml version="1.0" encoding="ISO-8859-1"?>
<GCompris>
  <Board 
	 type="draw" 
	 icon="boardicons/draw.png" 
	 author="Bruno Coudoin (bruno.coudoin at free.fr)"
	 boarddir="colornforms">
	 <name>A simple vector drawing tool</name>
	 <name xml:lang="de">Ein sehr einfaches Zeichenprogramm</name>
	 <name xml:lang="fr">Un outil simple de dessin vectoriel</name>
	 <description>Creative board were you can freely draw</description>
	 <description xml:lang="de">freie Fläche zum zeichenen</description>
	 <description xml:lang="fr">Tableau à vocation créative ou l'on peut dessiner librement</description>
  </Board>
</GCompris>
