<?xml version="1.0" encoding="UTF-8" standalone="no"?>
<GCompris>
<Wordlist name="default-gd" description="Gàidhlig" locale="gd">
<level value="1" sublevels="5">
a
e
i
o
u
</level>
<level value="2" sublevels="10">
1
2
3
4
5
6
7
8
9
</level>
<level value="3">
a
e
i
o
u
0
1
2
3
4
5
6
7
8
9
</level>
<level value="4" sublevels="12">
b
c
d
f
g
l
m
n
p
r
s
t
</level>
<level value="5">
b
c
d
f
g
l
m
n
p
r
s
t
0
1
2
3
4
5
6
7
8
9
</level>
<level value="6">
b
c
d
f
g
l
m
n
p
r
s
t
a
e
i
o
u
</level>
<level value="7" sublevels="5">
à
è
ì
ò
ù
</level>
<level value="8" sublevels="12">
bh
ch
dh
fh
gh
mh
ph
sh
th
ll
nn
rr
</level>
<level value="9">
à
è
ì
ò
ù
bh
ch
dh
fh
gh
mh
ph
sh
th
ll
nn
rr
</level>
<level value="10">
b
c
d
f
g
l
m
n
p
r
s
t
a
e
i
o
u
à
è
ì
ò
ù
bh
ch
dh
fh
gh
mh
ph
sh
th
ll
nn
rr
0
1
2
3
4
5
6
7
8
9
</level>
</Wordlist>
</GCompris>
